ideastatica_rcs_api/__init__.py
ideastatica_rcs_api/api_client.py
ideastatica_rcs_api/api_response.py
ideastatica_rcs_api/brief_result_tools.py
ideastatica_rcs_api/configuration.py
ideastatica_rcs_api/exceptions.py
ideastatica_rcs_api/helpers.py
ideastatica_rcs_api/loading_tools.py
ideastatica_rcs_api/py.typed
ideastatica_rcs_api/raw_results_tools.py
ideastatica_rcs_api/rcs_api_client.py
ideastatica_rcs_api/rcs_api_service_attacher.py
ideastatica_rcs_api/rcs_api_service_runner.py
ideastatica_rcs_api/rest.py
ideastatica_rcs_api/api/__init__.py
ideastatica_rcs_api/api/calculation_api.py
ideastatica_rcs_api/api/cross_section_api.py
ideastatica_rcs_api/api/design_member_api.py
ideastatica_rcs_api/api/internal_forces_api.py
ideastatica_rcs_api/api/project_api.py
ideastatica_rcs_api/api/section_api.py
ideastatica_rcs_api/api_ext/__init__.py
ideastatica_rcs_api/api_ext/project_ext_api.py
ideastatica_rcs_api/models/__init__.py
ideastatica_rcs_api/models/calculation_type.py
ideastatica_rcs_api/models/check_result.py
ideastatica_rcs_api/models/check_result_type.py
ideastatica_rcs_api/models/concrete_check_result.py
ideastatica_rcs_api/models/concrete_check_result_base.py
ideastatica_rcs_api/models/concrete_check_result_overall.py
ideastatica_rcs_api/models/concrete_check_result_overall_item.py
ideastatica_rcs_api/models/concrete_check_results.py
ideastatica_rcs_api/models/loading.py
ideastatica_rcs_api/models/loading_type.py
ideastatica_rcs_api/models/non_conformity.py
ideastatica_rcs_api/models/non_conformity_issue.py
ideastatica_rcs_api/models/non_conformity_severity.py
ideastatica_rcs_api/models/rcs_calculation_parameters.py
ideastatica_rcs_api/models/rcs_check_member.py
ideastatica_rcs_api/models/rcs_project.py
ideastatica_rcs_api/models/rcs_project_data.py
ideastatica_rcs_api/models/rcs_reinforced_cross_section.py
ideastatica_rcs_api/models/rcs_reinforced_cross_section_import_data.py
ideastatica_rcs_api/models/rcs_reinforced_crosss_section_import_setting.py
ideastatica_rcs_api-25.1.0.4141.dist-info/METADATA
ideastatica_rcs_api-25.1.0.4141.dist-info/WHEEL
ideastatica_rcs_api-25.1.0.4141.dist-info/top_level.txt
ideastatica_rcs_api-25.1.0.4141.dist-info/RECORD
