Metadata-Version: 2.1
Name: ideastatica-rcs-api
Version: 25.1.0.4141
Summary: RCS Rest API 1.0
Home-page: UNKNOWN
Author: IDEA StatiCa
Author-email: info@ideastatica.com
License: IDEA StatiCa License
Keywords: OpenAPI,OpenAPI-Generator,RCS Rest API 1.0
Platform: UNKNOWN
Requires-Dist: urllib3<3.0.0,>=1.25.3
Requires-Dist: python-dateutil>=2.8.2
Requires-Dist: pydantic>=2
Requires-Dist: typing-extensions>=4.7.1
